s3shell/__init__.py
s3shell/s3Func.py
s3shell/s3Shell.py
s3shell-0.1.dist-info/METADATA
s3shell-0.1.dist-info/WHEEL
s3shell-0.1.dist-info/entry_points.txt
s3shell-0.1.dist-info/top_level.txt
s3shell-0.1.dist-info/RECORD
